Workbook

Sheet General
C1: Units | D1: Comentarios (información de ayuda a la configuración - columna que no se ve en GUI)
A2: Project Lifetime | B2: 20 | C2: years | D2: Default value from Component_Database.xls --> Global data --> HOMER default
A3: Discount rate | B3: 8 | C3: % | D3: Only for post-process economic analysis. Source: Default value from Component_Database.xls --> Global data --> HOMER default
A4: Inflation rate | B4: 2 | C4: % | D4: Only for post-process economic analysis. Source: Default value from Component_Database.xls --> Global data --> HOMER default
A5: Cash change | B5: 1 | C5: €/$
A6: Operation cost of the reference case | C6: €/year | D6: <-- o bién se indica este coste o se debe realizar la optimización del caso de referencia
A7: Minimum share of renewables | B7: 0 | C7: %
A8: PV available surface | B8: 100000000 | C8: m2
A9: Discount rate optimization | B9: 0 | C9: %
A10: Emissions reference | C10: kgCO2/year | D10: <-- o bién se indica o se debe realizar la optimización del caso de referencia
A11: Minimum emissions reduction | B11: 0 | C11: %
A12: Electric network power flow | B12: DC-OPF | D12: type of power flow: economic_dispatch / DC-OPF
A13: Load not supplyed cost | B13: 1000 | C13: €/kWh
A14: CO2 emissions cost | B14: =70/1000 -> 0.07 | C14: €/kg | D14: including grid emissions

Sheet Load
A1: Identification number of each element. Each row represents an added element | C1: Type of load (AC, DC, EV) | D1: Identification number of the bus to which the load is connected | E1: Sheet "Load TS" has the time-series data of each load. This represents a coefficient for the time-series data
A2: id | B2: name | C2: type | D2: Bus | E2: Installed_power
A3: 1 | B3: Base load [kW] | D3: 1 | E3: 1
A4: 2 | B4: EV immediate charging [kW] | C4: EV | D4: 0 | E4: 0
A5: 3 | B5: aux grid | D5: 2 | E5: 1
A6: 4 | B6: aux islanded | D6: 3 | E6: 1

Sheet Load TS
A1: The tittle is the identification number of each element. Each column represents a different element. The value of each cell in one column is the load active power [kW or p.u.] of each hour, where each row represents an hour
A2: Time | B2: 1 | C2: 2 | D2: 3 | E2: 4 | F2: 5 | G2: 6 | H2: 7 | I2: 8 | J2: 9
A3: 43101 | B3: 69.913599 | C3: 0 | D3: 10 | E3: 20
A4: 43101.042 | B4: 71.005999 | C4: 0 | D4: 10 | E4: 20
A5: 43101.083 | B5: 65.543999 | C5: 0 | D5: 10 | E5: 20
A6: 43101.125 | B6: 68.821199 | C6: 0 | D6: 10 | E6: 20
A7: 43101.167 | B7: 71.005999 | C7: 0 | D7: 10 | E7: 20
A8: 43101.208 | B8: 66.636399 | C8: 0 | D8: 10 | E8: 20
A9: 43101.25 | B9: 69.913599 | C9: 0 | D9: 10 | E9: 20
A10: 43101.292 | B10: 71.005999 | C10: 0 | D10: 10 | E10: 20
A11: 43101.333 | B11: 57.897199 | C11: 0 | D11: 10 | E11: 20
A12: 43101.375 | B12: 57.897199 | C12: 0 | D12: 10 | E12: 20
A13: 43101.417 | B13: 55.712399 | C13: 0 | D13: 10 | E13: 20
A14: 43101.458 | B14: 49.158 | C14: 0 | D14: 10 | E14: 20
... A8762: 43465.958 | B8762: 72.098399 | C8762: 0 | D8762: 10 | E8762: 20

Sheet PV
C1: from the database | D1: Identification number of the bus to which the load is connected | E1: 1: new PV can be added 0: no | F1: PV installed capacity already in the system [kW] | G1: if the sizing is fixed, the PV install capacity to add [kW] | H1: incentives on the capex [€/kW] | I1: 1: PVGIS 0: timeseries | J1: [º] | K1: [º] | L1: Inclination angle [º] from horizontal plane | M1: Orientation (azimuth) angle [º] of the (fixed) plane, 0=south, 90=west, -90=east | N1: Calculate the optimum inclination angle. Value of 1 for "yes". | O1: Calculate the optimum inclination AND orientation angles. Value of 1 for "yes". | P1: --> PVGIS-SARAH (Europe, Africa and Asia), PVGIS-NSRDB (the Americas between 60°N and 20°S), PVGIS-ERA5 and PVGIS-COSMO for Europe (including high-latitudes), and PVGIS-CMSAF for Europe and Africa (will be deprecated). Default by location | Q1: --> crystSi, CIS, CdTe, Unknown. Default = crystSi | R1: --> 0=fixed, 1=single horizontal axis aligned north-south, 2=two-axis tracking, 3=vertical axis tracking, 4=single horizontal axis aligned east-west, 5=single inclined axis aligned north-south
A2: id | B2: name | C2: model | D2: Bus | E2: sizing | F2: existent | G2: fix | H2: incentives | I2: forecast | J2: Latitude | K2: Longitude | L2: Slope | M2: Azimuth | N2: Optimal slope | O2: Optimal slope and azimuth | P2: Radiation database | Q2: PV technology | R2: Suntracking type
A3: 1 | B3: PV1 | C3: General PV | D3: 1 | E3: 1 | F3: 700 | H3: 0 | I3: 0 | J3: 41.397 | K3: 2.155 | L3: 35 | M3: 180

Sheet PV TS
A1: The tittle is the identification number of each element. Each column represents a different element. The value of each cell in one column is the load active power [kW or p.u.] of each hour, where each row represents an hour
A2: Time | B2: 1 | C2: 2 | D2: 3 | E2: 4 | F2: 5 | G2: 6 | H2: 7 | I2: 8 | J2: 9
A3: 43101 | B3: 0
A4: 43101.042 | B4: 0
A5: 43101.083 | B5: 0
A6: 43101.125 | B6: 0
A7: 43101.167 | B7: 0
A8: 43101.208 | B8: 0
A9: 43101.25 | B9: 0
A10: 43101.292 | B10: 0
A11: 43101.333 | B11: 0.2144025
A12: 43101.375 | B12: 0.46633275
A13: 43101.417 | B13: 0.6402045
A14: 43101.458 | B14: 0.70438875
... A8762: 43465.958 | B8762: 0

Sheet PV database
A1: Photovoltaic | B1: Capital | C1: Replacement | D1: O&M | E1: Bus | F1: Lifetime | G1: Derating | H1: DNI rating | I1: Tracking | J1: Temp. Effect | K1: Nomin. Temp. | L1: Nomin. Effic.
A2: Unit | B2: ? | C2: ? | D2: ?/year | E2: AC or DC | F2: Year | G2: % | H2: kW/m² | I2: method | J2: %/°C | K2: °C | L2: %
A3: HOMER data | B3: Y | C3: Y | D3: Y | E3: Y | F3: Y | G3: Y | H3: Y | I3: Y | J3: Y | K3: Y | L3: Y
A4: PV h2glass | B4: 650 | C4: =0.5*B4 -> 325 | D4: =0.02*B4 -> 13 | E4: DC | F4: 20 | H4: 0.85
A5: General PV | B5: 800 | C5: 800 | D5: 14 | E5: DC | F5: 25 | H5: 0.85
A6: Generic flat plate PV | B6: 3000 | C6: 3000 | D6: 10 | E6: DC | F6: 25 | G6: 80 | H6: 0.85 | I6: No tracking

Sheet BESS
C1: from the database | D1: Identification number of the bus to which the load is connected | E1: 1: new batteries can be added 0: no | F1: Number of batteries already in the system [u] | G1: if the sizing is fixed, the number of batteries to add [u] | H1: incentives on the capex [€/kWh]
A2: id | B2: name | C2: model | D2: Bus | E2: sizing | F2: existent | G2: fix | H2: incentives
A3: 1 | B3: BESS1 | C3: General BESS | D3: 1 | E3: 1 | F3: 0 | H3: 0

Sheet Battery database
A1: Battery | B1: Available in… | D1: Capacity (kWh) | E1: Manufacturer | F1: Capital | G1: Replacement | H1: O&M | I1: Bus | J1: Lifetime | K1: Throughput | L1: SOC min | M1: Voltage nom. | N1: Capacity | O1: Roudtrip eff. | P1: Max charge | Q1: Max discharge | R1: Max charge (kW) | S1: Max discharge (kW) | T1: SOC max | U1: Self-discharge rate (hourly) | V1: Charge eff. | W1: Discharge eff. | X1: Calendar aging (anual) | Y1: Degradation cost
A2: Unit | B2: HOMER | C2: DiSiPl | D2: kWh | E2: web site | F2: [cur] | G2: [cur] | H2: [cur]/year | I2: AC or DC | J2: Year | K2: kWh | L2: % | M2: V | N2: Ah | O2: % | P2: A | Q2: A | R2: kW | S2: kW | T2: % | U2: % | V2: % | W2: % | X2: % | Y2: €/kWh
A3: HOMER data | D3: Y | E3: Y | F3: Y | G3: Y | H3: Y | I3: Y | J3: Y | K3: Y | L3: Y | M3: Y | N3: Y | O3: Y | P3: Y | Q3: Y
A4: BESS h2glass | D4: 100 | F4: =306*D4 -> 30600 | G4: =0.5*F4 -> 15300 | H4: =0.02*F4 -> 612 | J4: 10 | K4: 1000000 | L4: 20 | R4: 100 | S4: 100 | T4: 100 | U4: =5/30/24 -> 0.0069444444 | V4: 95 | W4: 95 | X4: 1.5 | Y4: =0.01/25 -> 0.0004
A5: General BESS | D5: 1 | F5: 260 | G5: 260 | H5: 10 | I5: DC | J5: =J6 -> 15 | K5: =K6 -> 3000 | L5: =L6 -> 10 | M5: =M6 -> 6 | N5: =N6 -> 166.667 | O5: =O6 -> 90 | P5: =P6 -> 166.6667 | Q5: =P5 -> 166.6667 | R5: =P5*M5/1000 -> 1.0000002 | S5: =Q5*M5/1000 -> 1.0000002 | T5: 100 | U5: =5/30/24 -> 0.0069444444 | V5: 95 | W5: 95 | X5: 1.5 | Y5: =0.01/25 -> 0.0004
A6: Generic 1kWh Li-Ion | B6: Y | C6: Y | D6: 1 | E6: Generic | F6: 600 | G6: 600 | H6: 10 | I6: DC | J6: 15 | K6: 3000 | L6: 10 | M6: 6 | N6: 166.667 | O6: 90 | P6: 166.6667 | Q6: 500 | R6: =P6*M6/1000 -> 1.0000002 | S6: =Q6*M6/1000 -> 3 | T6: 100 | U6: =5/30/24 -> 0.0069444444 | V6: 95 | W6: 95 | X6: 1.5 | Y6: =0.01/25 -> 0.0004
A7: Generic 1kWh Lead Acid | B7: Y | C7: Y | D7: 1 | E7: Generic | F7: 300 | G7: 300 | H7: 10 | I7: DC | J7: 10 | K7: 800 | L7: 40 | M7: 12 | N7: 83.4 | O7: 80 | P7: 16.7 | Q7: 24.3 | R7: =P7*M7/1000 -> 0.2004 | S7: =Q7*M7/1000 -> 0.2916
A8: Generic Vanadium | B8: Y | C8: Y | D8: 1 | E8: Generic | F8: 5000 | G8: 1000 | H8: 100 | I8: DC | J8: 15 | K8: Inf | L8: 20
A9: Schneider BESS 125 kW Li-Ion | B9: Y | C9: Y | D9: 253.3 | E9: LG Chem/ Parker | F9: =750*D9 -> 189975 | G9: =500*D9 -> 126650 | H9: =10*D9 -> 2533 | I9: DC | J9: 15 | K9: =4000*D9 -> 1013200 | L9: 10 | M9: 880 | O9: 91 | R9: 125 | S9: 125
A10: Schneider BESS 250 kW Li-Ion | B10: Y | C10: Y | D10: 570 | E10: LG Chem/ Parker | F10: =750*D10 -> 427500 | G10: =500*D10 -> 285000 | H10: =10*D10 -> 5700 | I10: DC | J10: 15 | K10: =4000*D10 -> 2280000 | L10: 10 | M10: 880 | O10: 91 | R10: 250 | S10: 250
A11: Schneider BESS 500 kW Li-Ion | B11: Y | C11: Y | D11: 1140 | E11: LG Chem/ Parker | F11: =750*D11 -> 855000 | G11: =500*D11 -> 570000 | H11: =10*D11 -> 11400 | I11: DC | J11: 15 | K11: =4000*D11 -> 4560000 | L11: 10 | M11: 880 | O11: 91 | R11: 500 | S11: 500
A12: Schneider BESS 1000 kW Li-Ion | B12: Y | C12: Y | D12: 2089 | E12: LG Chem/ Parker | F12: =750*D12 -> 1566750 | G12: =500*D12 -> 1044500 | H12: =10*D12 -> 20890 | I12: DC | J12: 15 | K12: =4000*D12 -> 8356000 | L12: 10 | M12: 880 | O12: 91 | R12: 1000 | S12: 1000
A13: Schneider BESS 62,5 kW Li-Ion | B13: Y | C13: Y | D13: 108 | E13: LG Chem/ Parker | F13: =500*D13 -> 54000 | G13: =400*D13 -> 43200 | H13: =10*D13 -> 1080 | I13: DC | J13: 15 | K13: =4000*D13 -> 432000 | L13: 10 | M13: 880 | O13: 91 | R13: 62.5 | S13: 62.5
A14: Schneider BESS 375 kW Li-Ion | B14: Y | C14: Y | D14: 432 | E14: LG Chem/ Parker | F14: =500*D14 -> 216000 | G14: =400*D14 -> 172800 | H14: =10*D14 -> 4320 | I14: DC | J14: 15 | K14: =4000*D14 -> 1728000 | L14: 10 | M14: 880 | O14: 91 | R14: 375 | S14: 375

Sheet Economic Constraints
A1: Constraint | B1: Enable | C1: Variable | D1: Expression | E1: Value | F1: Units
A2: ROI <= k | B2: 0 | C2: ROI | D2: <= | E2: 0 | F2: %
A3: ROI >= k | B3: 0 | C3: ROI | D3: >= | E3: 0 | F3: %
A4: ROI == k | B4: 0 | C4: ROI | D4: == | E4: 0 | F4: %
A5: payback <= k | B5: 0 | C5: payback | D5: <= | E5: 0 | F5: years
A6: payback >= k | B6: 0 | C6: payback | D6: >= | E6: 0 | F6: years
A7: payback == k | B7: 0 | C7: payback | D7: == | E7: 0 | F7: years
A8: investment <= k | B8: 0 | C8: investment | D8: <= | E8: 0 | F8: €
A9: investment >= k | B9: 0 | C9: investment | D9: >= | E9: 0 | F9: €
A10: investment == k | B10: 0 | C10: investment | D10: == | E10: 0 | F10: €

Sheet Grid
A1: Identification number of each element. Each row represents an added element | D1: --> Spanish, Portuguese Portuguesse tariff not considered yet | E1: --> Peninsula, Canarias, Baleares, Ceuta, Melilla | F1: Tarifa 2.0TD: <1 kV, Potencia contratada ≤ 15 kW Tarifa 3.0TD: < 1kV, Potencia contratada > 15kW Tarifa 6.1TD: 1 kV < tensión < 30 kV Tarifa 6.2TD: 30 kV <= tensión < 72.5 kV Tarifa 6.3TD: 72.5 kV <= tensión < 145 kV Tarifa 6.4TD: > 145 kV | G1: Tipo 1: potencia contratada ≥ 10 MW Tipo 2: 450 kW ≤ potencia contratada < 10 MW Tipo 3: 50 kW < potencia contratada < 450 kW Tipo 4: 15 kW < potencia contratada ≤ 50 kW Tipo 5: potencia contratada ≤ 15 kW | H1: 1: yes, 0: no | I1: --> Fix, By period, Annual, Upload Where Annual means from the market internal data, and Upload means you upload the annual cost | J1: [€/kWh] | K1: [€/kWh] If annual, a fee is added to the API (excel) price | L1: --> Fix, By period, Annual, Upload | M1: [€/kWh] | N1: [€/kWh] If annual, a fee is substracted from the API (excel) price | O1: User will to inject power to the grid (1: yes, 0: no) | P1: [kW] PV install power limit to decide to inject or not to the grid | Q1: Optional, maximum power exchanged with the grid (both buy and sell) | R1: 1: Spanish national grid 0: timeseries
A2: id | B2: name | C2: Bus | D2: Tariff country | E2: Territory | F2: Tariff | G2: Meter type | H2: Fix hired power | I2: Buy energy price type | J2: Fix buy energy price | K2: Buy energy price fee | L2: Sell energy price type | M2: Fix sell energy price | N2: Sell energy price fee | O2: Inyection to the grid | P2: PV power limit to inject | Q2: Hard power limit | R2: Emissions/renewables share source type
A3: 1 | B3: grid of load 1 | C3: 0 | D3: Spanish | E3: Peninsula | F3: 2.0TD | H3: 0 | I3: Upload | L3: Upload | O3: 1 | P3: 100 | R3: 0
A4: 2 | B4: grid of load 2 | C4: 2 | D4: Spanish | E4: Peninsula | F4: 3.0TD | H4: 0 | I4: By period | L4: By period | O4: 1 | P4: 100 | R4: 0

Sheet hired_power Periods
A1: The tittle is the identification number of each element. Each column represents a different element. The value of each cell in one column is the hired power [kW] of each tariff period, where each row represents a tariff period
A2: Period | B2: 1 | C2: 2 | D2: 3 | E2: 4
A3: P1 | B3: 80 | C3: 4 | D3: 10 | E3: 5
A4: P2 | B4: 80 | C4: 4 | D4: 10 | E4: 5
A5: P3 | B5: 80 | C5: 4 | D5: 10 | E5: 5
A6: P4 | B6: 80 | C6: 4 | D6: 10 | E6: 5
A7: P5 | B7: 80 | C7: 4 | D7: 10 | E7: 5
A8: P6 | B8: 80 | C8: 4 | D8: 10 | E8: 5

Sheet buy_price Periods
A1: The tittle is the identification number of each element. Each column represents a different element. The value of each cell in one column is the buy price [€/kW] of each tariff period, where each row represents a tariff period
A2: Period | B2: 1 | C2: 2 | D2: 3 | E2: 4
A3: P1 | B3: 0.05 | C3: 0.05 | D3: 0.05 | E3: 0.08
A4: P2 | B4: 0.05 | C4: 0.05 | D4: 0.05 | E4: 0.08
A5: P3 | B5: 0.05 | C5: 0.05 | D5: 0.05 | E5: 0.08
A6: P4 | B6: 0.05 | C6: 0.05 | D6: 0.05 | E6: 0.08
A7: P5 | B7: 0.05 | C7: 0.05 | D7: 0.05 | E7: 0.08
A8: P6 | B8: 0.05 | C8: 0.05 | D8: 0.05 | E8: 0.08

Sheet sell_price Periods
A1: The tittle is the identification number of each element. Each column represents a different element. The value of each cell in one column is the sell price [€/kW] of each tariff period, where each row represents a tariff period
A2: Period | B2: 1 | C2: 2 | D2: 3 | E2: 4
A3: P1 | B3: 0 | C3: 0 | D3: 0 | E3: 0
A4: P2 | B4: 0 | C4: 0 | D4: 0 | E4: 0
A5: P3 | B5: 0 | C5: 0 | D5: 0 | E5: 0
A6: P4 | B6: 0 | C6: 0 | D6: 0 | E6: 0
A7: P5 | B7: 0 | C7: 0 | D7: 0 | E7: 0
A8: P6 | B8: 0 | C8: 0 | D8: 0 | E8: 0

Sheet buy_price TS
A1: The tittle is the identification number of each element. Each column represents a different element. The value of each cell in one column is the buy price [€/kW] of each hour, where each row represents an hour
A2: Time | B2: 1 | C2: 2
A3: 44927 | B3: 0.04145 | C3: 0.05
A4: 44927.042 | B4: 0.04301 | C4: 0.05
A5: 44927.083 | B5: 0.05807 | C5: 0.05
A6: 44927.125 | B6: 0.06069 | C6: 0.05
A7: 44927.167 | B7: 0.06291 | C7: 0.05
A8: 44927.208 | B8: 0.06148 | C8: 0.05
A9: 44927.25 | B9: 0.06301 | C9: 0.05
A10: 44927.292 | B10: 0.06032 | C10: 0.05
A11: 44927.333 | B11: 0.06793 | C11: 0.05
A12: 44927.375 | B12: 0.06465 | C12: 0.05
A13: 44927.417 | B13: 0.05984 | C13: 0.05
A14: 44927.458 | B14: 0.05638 | C14: 0.05
... A8762: 45291.958 | B8762: 0.10523 | C8762: 0.05

Sheet sell_price TS
A1: The tittle is the identification number of each element. Each column represents a different element. The value of each cell in one column is the sell price [€/kW] of each hour, where each row represents an hour
A2: Time | B2: 1 | C2: 2
A3: 44927 | B3: ='buy_price TS'!B3/2 -> 0.020725 | C3: 0
A4: 44927.042 | B4: ='buy_price TS'!B4/2 -> 0.021505 | C4: 0
A5: 44927.083 | B5: ='buy_price TS'!B5/2 -> 0.029035 | C5: 0
A6: 44927.125 | B6: ='buy_price TS'!B6/2 -> 0.030345 | C6: 0
A7: 44927.167 | B7: ='buy_price TS'!B7/2 -> 0.031455 | C7: 0
A8: 44927.208 | B8: ='buy_price TS'!B8/2 -> 0.03074 | C8: 0
A9: 44927.25 | B9: ='buy_price TS'!B9/2 -> 0.031505 | C9: 0
A10: 44927.292 | B10: ='buy_price TS'!B10/2 -> 0.03016 | C10: 0
A11: 44927.333 | B11: ='buy_price TS'!B11/2 -> 0.033965 | C11: 0
A12: 44927.375 | B12: ='buy_price TS'!B12/2 -> 0.032325 | C12: 0
A13: 44927.417 | B13: ='buy_price TS'!B13/2 -> 0.02992 | C13: 0
A14: 44927.458 | B14: ='buy_price TS'!B14/2 -> 0.02819 | C14: 0
... A8762: 45291.958 | B8762: ='buy_price TS'!B8762/2 -> 0.052615 | C8762: 0

Sheet Grid_emissions TS
A1: The tittle is the identification number of each element. Each column represents a different element. The value of each cell in one column is the emission factor [t CO2/MWh] of each hour, where each row represents an hour
A2: Time | B2: 1 | C2: 2 | D2: 3 | E2: 4 | F2: 5 | G2: 6 | H2: 7 | I2: 8 | J2: 9
A3: 43101 | B3: 0 | C3: 0 | D3: 0.095848151
A4: 43101.042 | B4: 0 | C4: 0 | D4: 0.10511611
A5: 43101.083 | B5: 0 | C5: 0 | D5: 0.10589707
A6: 43101.125 | B6: 0 | C6: 0 | D6: 0.11328886
A7: 43101.167 | B7: 0 | C7: 0 | D7: 0.11613194
A8: 43101.208 | B8: 0 | C8: 0 | D8: 0.11646374
A9: 43101.25 | B9: 0 | C9: 0 | D9: 0.12064519
A10: 43101.292 | B10: 0 | C10: 0 | D10: 0.12231477
A11: 43101.333 | B11: 0 | C11: 0 | D11: 0.12049679
A12: 43101.375 | B12: 0 | C12: 0 | D12: 0.11305309
A13: 43101.417 | B13: 0 | C13: 0 | D13: 0.097330152
A14: 43101.458 | B14: 0 | C14: 0 | D14: 0.090659153
... A8762: 43465.958 | B8762: 0 | C8762: 0 | D8762: 0.060484131

Sheet Grid_renewables TS
A1: The tittle is the identification number of each element. Each column represents a different element. The value of each cell in one column is the renewables share [pu] of each hour, where each row represents an hour
A2: Time | B2: 1 | C2: 2 | D2: 3 | E2: 4 | F2: 5 | G2: 6 | H2: 7 | I2: 8 | J2: 9
A3: 43101 | B3: 1 | C3: 1 | D3: 0.2
A4: 43101.042 | B4: 1 | C4: 1 | D4: 0.2
A5: 43101.083 | B5: 1 | C5: 1 | D5: 0.2
A6: 43101.125 | B6: 1 | C6: 1 | D6: 0.2
A7: 43101.167 | B7: 1 | C7: 1 | D7: 0.2
A8: 43101.208 | B8: 1 | C8: 1 | D8: 0.2
A9: 43101.25 | B9: 1 | C9: 1 | D9: 0.2
A10: 43101.292 | B10: 1 | C10: 1 | D10: 0.2
A11: 43101.333 | B11: 1 | C11: 1 | D11: 0.2
A12: 43101.375 | B12: 1 | C12: 1 | D12: 0.2
A13: 43101.417 | B13: 1 | C13: 1 | D13: 0.2
A14: 43101.458 | B14: 1 | C14: 1 | D14: 0.2
... A8762: 43465.958 | B8762: 1 | C8762: 1 | D8762: 0.2

Sheet EV
C1: Units | D1: Comentarios (información de ayuda a la configuración - columna que no se ve en GUI)
A2: EV (1: yes, 0: no) | B2: 1 | D2: Select if the system contains EV to build annual profile (if immediate charging and annual profile is given, input EV as Load)
A3: Bus | B3: 0
A4: Model EV | D4: Not considered yet
A5: Smart charging (1) or Immediate charging (0) | B5: 1
A6: Number of vehicles | B6: 1
A7: Number of charging points | B7: 1 | D7: De moment només preparat per 1 punt de càrrega
A8: Maximum charging power of the EV battery | B8: 250 | C8: kW
A9: Maximum power of the charging point | B9: 250 | C9: kW
A10: Maximum power of the charging station | B10: 250 | C10: kW
A11: Flexibility cost | B11: 0 | C11: €
A12: Vehicles arrivals | D12: Currently, arrival and parked time must be within the 24h of a day (to improve)
A13: Probability distribution arrivals (1: Normal, 0: Uniform) | B13: 1
A14: 1st parameter arrivals | B14: 12 | D14: 1st parameter (hora media si Normal, hora mínimo si Uniforme)
A15: 2nd parameter arrivals | B15: 2 | D15: 2nd parameter (desv. est. si Normal, hora máximo si Uniforme)
A16: Days | B16: Lu-Vi | D16: --> todos los dias, Lu-Vi, fin de semana
A17: Parked time
A18: Probability distribution parked (1: Normal, 0: Uniform) | B18: 1
A19: 1st parameter parked | B19: 8 | D19: 1st parameter (hora media si Normal, hora mínimo si Uniforme)
A20: 2nd parameter parked | B20: 2 | D20: 2nd parameter (desv. est. si Normal, hora máximo si Uniforme)

Sheet Bus
E1: Not considered yet | F1: Not considered yet | G1: Not considered yet
A2: Num | B2: name | C2: type | D2: vn_kv | E2: slack | F2: v_pu_min | G2: v_pu_max
A3: 0 | B3: bus0 | C3: AC | D3: 40 | E3: 1 | F3: 0.9 | G3: 1.05
A4: 1 | B4: bus1 | C4: AC | D4: 40 | E4: 0 | F4: 0.9 | G4: 1.05
A5: 2 | B5: bus2 | C5: AC | D5: 40 | E5: 0 | F5: 0.9 | G5: 1.05
A6: 3 | B6: bus3 | C6: AC | D6: 40 | E6: 0 | F6: 0.9 | G6: 1.05

Sheet Lines
E1: only in DC-OPF | F1: only in AC-OPF
A2: id | B2: name | C2: from_bus | D2: to_bus | E2: P_max (kW) | F2: I_max (A) | G2: R (Ω) | H2: X (Ω) | I2: B (S)
A3: 1 | B3: line1 | C3: 0 | D3: 1 | E3: 9000 | F3: 9000 | G3: 2 | H3: 2 | I3: 0
